fhmediacollector/__init__.py
fhmediacollector-1.1.4.dist-info/METADATA
fhmediacollector-1.1.4.dist-info/WHEEL
fhmediacollector-1.1.4.dist-info/entry_points.txt
fhmediacollector-1.1.4.dist-info/top_level.txt
fhmediacollector-1.1.4.dist-info/RECORD
