Metadata-Version: 2.1
Name: fhmediacollector
Version: 1.1.4
Summary: e621 media collection and organization for video creation
Home-page: https://github.com/oddpawsx/fhmediacollector
Author: OddPawsX
Author-email: 78638049+oddpawsx@users.noreply.github.com
License: UNKNOWN
Platform: UNKNOWN
Requires-Dist: requests
Requires-Dist: python-dotenv
